{
  "products": [
    {
      "id": "1",
      "name": "anhntph43180@fpt.edu12341243125245.vn",
      "image": "https://cdn2.cellphones.com.vn/358x358,webp,q100/media/catalog/product/d/v/dvfdgty_5_.jpg",
      "price": "1231431",
      "cate": "áo"
    },
    {
      "name": "anhnt12345678",
      "image": "https://cdn2.cellphones.com.vn/358x358,webp,q100/media/catalog/product/s/a/samsung_galaxy_z_fold_4-7.jpg",
      "price": "1234561234567",
      "cate": "giay",
      "id": "25ab"
    },
    {
      "name": "anhnt12345678",
      "image": "https://cdn2.cellphones.com.vn/358x358,webp,q100/media/catalog/product/s/a/samsung_galaxy_z_fold_4-7.jpg",
      "price": "1234561234567",
      "cate": "giay",
      "id": "25ab"
    },
    {
      "id": "40c6",
      "name": "anhnt12345678",
      "image": "https://cdn2.cellphones.com.vn/358x358,webp,q100/media/catalog/product/s/a/samsung_galaxy_z_fold_4-7.jpg",
      "price": "234",
      "cate": "dep"
    },
    {
      "name": "123134de2ggbvg",
      "image": "https://cdn2.cellphones.com.vn/358x358,webp,q100/media/catalog/product/d/v/dvfdgty_5_.jpg",
      "price": "12321343546576",
      "cate": "dep",
      "id": "55ed"
    }
  ],
  "users": [
    {
      "id": "1",
      "username": "anhnt",
      "password": "123"
    }
  ]
}